{
  "insert-template": [
    {
      "modifiers": [
        "Alt"
      ],
      "key": "T"
    }
  ],
  "podnotes:capture-timestamp": [
    {
      "modifiers": [
        "Mod"
      ],
      "key": " "
    }
  ],
  "podnotes:skip-forward": [],
  "editor:toggle-highlight": [
    {
      "modifiers": [
        "Mod",
        "Shift"
      ],
      "key": "H"
    }
  ],
  "editor:cycle-list-checklist": [
    {
      "modifiers": [
        "Mod",
        "Shift"
      ],
      "key": "C"
    }
  ],
  "obsidian-timestamp-notes:timestamp-insert": [
    {
      "modifiers": [
        "Mod"
      ],
      "key": "T"
    }
  ],
  "workspace:new-tab": [],
  "obsidian-timestamp-notes:trigger-player": [
    {
      "modifiers": [
        "Mod",
        "Shift"
      ],
      "key": "O"
    }
  ],
  "insert-current-time": [
    {
      "modifiers": [
        "Mod",
        "Shift"
      ],
      "key": "I"
    }
  ],
  "obsidian-book-search-plugin:open-book-search-modal": [
    {
      "modifiers": [
        "Mod",
        "Shift"
      ],
      "key": "B"
    }
  ],
  "daily-notes": [
    {
      "modifiers": [
        "Alt"
      ],
      "key": "D"
    }
  ],
  "darlal-switcher-plus:switcher-plus:open-headings": [
    {
      "modifiers": [
        "Mod",
        "Shift"
      ],
      "key": "L"
    }
  ],
  "yet-another-obsidian-synchronizer:sync": [
    {
      "modifiers": [
        "Mod",
        "Shift"
      ],
      "key": "S"
    }
  ],
  "yet-another-obsidian-synchronizer:show-unmerged": [
    {
      "modifiers": [
        "Mod",
        "Shift"
      ],
      "key": "U"
    }
  ]
}